directmultistep/__init__.py
directmultistep/generate.py
directmultistep/helpers.py
directmultistep/analysis/__init__.py
directmultistep/analysis/style.py
directmultistep/analysis/training.py
directmultistep/analysis/paper/__init__.py
directmultistep/analysis/paper/dataset_analysis.py
directmultistep/analysis/paper/linear_vs_convergent.py
directmultistep/generation/__init__.py
directmultistep/generation/eval.py
directmultistep/generation/generation.py
directmultistep/generation/tensor_gen.py
directmultistep/model/__init__.py
directmultistep/model/architecture.py
directmultistep/model/config.py
directmultistep/model/factory.py
directmultistep/model/components/__init__.py
directmultistep/model/components/attention.py
directmultistep/model/components/decoder.py
directmultistep/model/components/encoder.py
directmultistep/model/components/moe.py
directmultistep/model/default_configs/__init__.py
directmultistep/model/default_configs/deep_40M.yaml
directmultistep/model/default_configs/explorer_19M.yaml
directmultistep/model/default_configs/explorer_xl_50M.yaml
directmultistep/model/default_configs/flash_10M.yaml
directmultistep/model/default_configs/flash_20M.yaml
directmultistep/model/default_configs/flex_20M.yaml
directmultistep/model/default_configs/wide_40M.yaml
directmultistep/training/__init__.py
directmultistep/training/config.py
directmultistep/training/lightning.py
directmultistep/training/trainer.py
directmultistep/utils/__init__.py
directmultistep/utils/dataset.py
directmultistep/utils/io.py
directmultistep/utils/logging_config.py
directmultistep/utils/post_process.py
directmultistep/utils/pre_process.py
directmultistep/utils/web_visualize.py
directmultistep-1.1.3.dist-info/licenses/LICENSE
directmultistep-1.1.3.dist-info/METADATA
directmultistep-1.1.3.dist-info/WHEEL
directmultistep-1.1.3.dist-info/top_level.txt
directmultistep-1.1.3.dist-info/RECORD
