Metadata-Version: 2.4
Name: directmultistep
Version: 1.1.3
Author-email: Anton Morgunov <anton@ischemist.com>, Yu Shee <yu.shee@yale.edu>
License: MIT
Project-URL: Homepage, https://github.com/batistagroup/DirectMultiStep
Project-URL: Issues, https://github.com/batistagroup/DirectMultiStep/issues
Requires-Python: >=3.11
License-File: LICENSE
Requires-Dist: numpy>=1.26.4
Requires-Dist: lightning>=2.2.5
Requires-Dist: pyyaml>=6.0.1
Requires-Dist: rdkit>=2023.9.3
Requires-Dist: torch>=2.3.0
Requires-Dist: tqdm>=4.67.1
Provides-Extra: vis
Requires-Dist: svgwrite>=1.4.3; extra == "vis"
Requires-Dist: svglib>=1.5.1; extra == "vis"
Requires-Dist: plotly>=5.24.1; extra == "vis"
Dynamic: license-file
